watergeo/__init__.py
watergeo/common.py
watergeo/foliumap.py
watergeo/utility.py
watergeo/watergeo.py
watergeo-0.1.1.dist-info/LICENSE
watergeo-0.1.1.dist-info/METADATA
watergeo-0.1.1.dist-info/WHEEL
watergeo-0.1.1.dist-info/entry_points.txt
watergeo-0.1.1.dist-info/top_level.txt
watergeo-0.1.1.dist-info/RECORD
