Metadata-Version: 2.1
Name: watergeo
Version: 0.1.1
Summary: python package for water spatial analysis
Author-email: Xinming Zhang <andyzxm1101@gmail.com>
License: MIT License
Project-URL: Homepage, https://github.com/Xinming Andy Zhang/watergeo
Keywords: watergeo
Classifier: Intended Audience :: Developers
Classifier: License :: OSI Approved :: MIT License
Classifier: Natural Language :: English
Classifier: Programming Language :: Python :: 3.8
Classifier: Programming Language :: Python :: 3.9
Classifier: Programming Language :: Python :: 3.10
Classifier: Programming Language :: Python :: 3.11
Classifier: Programming Language :: Python :: 3.12
Requires-Python: >=3.8
License-File: LICENSE
Requires-Dist: numpy
Requires-Dist: leafmap
Requires-Dist: geopandas
Requires-Dist: ipyleaflet
Requires-Dist: pandas
Requires-Dist: earthengine-api >=0.1.398
Requires-Dist: ee
Requires-Dist: folium
Requires-Dist: localtileserver
Provides-Extra: all
Requires-Dist: watergeo[extra] ; extra == 'all'
Provides-Extra: extra
Requires-Dist: pandas ; extra == 'extra'
